{
    "expediente": "21/2025",
    "pertenencia": "PRIMERA SALA",
    "ministro": "ALFREDO GUTIÉRREZ ORTIZ MENA",
    "resolucion": "1.\tES INFUNDADO EL RECURSO DE RECLAMACIÓN.\r\n2.\tSE CONFIRMA EL ACUERDO RECURRIDO.",
    "votacion": "POR UNANIMIDAD DE CINCO VOTOS DE LOS SEÑORES MINISTROS ALFREDO GUTIÉRREZ ORTIZ MENA (PONENTE), JUAN LUIS GONZÁLEZ ALCÁNTARA CARRANCÁ, ANA MARGARITA RÍOS FARJAT Y PRESIDENTA LORETTA ORTIZ AHLF, JORGE MARIO PARDO REBOLLEDO.",
    "urlInternet": "https://www2.scjn.gob.mx/juridica/engroses/1/2025/17/2_344691_7299.docx",
    "tema": "R.R. EN EL VARIOS 1970/2024\r\n\r\nCLASIFICACIÓN: OTROS - INCOMPETENTE\r\n\r\nMECM/MZD",
    "organoJurisdiccionalOrigen": "",
    "organoResolvio": "PRIMERA SALA",
    "huellaDigital": "3414fa2325b51704343f249566444ee64cb281c80a6cf5a141cc6543c9c2b0cf",
    "fechaResolucion": "09/04/2025"
}