{
    "expediente": "5608/2025",
    "pertenencia": "PLENO",
    "ministro": "MARÍA ESTELA RÍOS GONZÁLEZ",
    "resolucion": "ÚNICO: Queda sin materia el amparo directo en revisión a que este expediente se refiere.",
    "votacion": "Así lo resolvió el Pleno de la Suprema Corte de Justicia de la Nación por mayoría de seis votos de las personas Ministras Herrerías Guerra, Espinosa Betanzo, Esquivel Mossa, Batres Guadarrama, Ortiz Ahlf y Guerrero García. Las personas Ministras Ríos González, Figueroa Mejía y Presidente Aguilar Ortiz votaron en contra.\r\n\r\nEl señor Ministro Presidente Aguilar Ortiz declaró que el asunto se resolvió en los términos precisados.",
    "urlInternet": "https://www2.scjn.gob.mx/juridica/engroses/3/2025/10/2_355021_7421.docx",
    "tema": "JUICIO DE NULIDAD EN CONTRA DE UN CRÉDITO FISCAL \r\n\r\nPOSIBLE TEMA DE PROCEDENCIA: ARTÍCULOS 24, 25, PÁRRAFOS PRIMERO Y CUARTO, 31, FRACCIÓN I, 32, FRACCIÓN XVIII, INCISOS A), B), C) Y D); Y 68 DE LA LEY DEL IMPUESTO SOBRE LA RENTA\r\n\r\nJOVT/izso\r\n\r\nARTÍCULO 25, PRIMER Y CUARTO PÁRRAFOS, DE LA LEY DEL IMPUESTO SOBRE LA RENTA VIGENTE EN EL EJERCICIO FISCAL DE DOS MIL DIEZ.  ",
    "organoJurisdiccionalOrigen": "TRIBUNAL DE ORIGEN: SEGUNDO TRIBUNAL COLEGIADO EN MATERIA ADMINISTRATIVA DEL PRIMER CIRCUITO ",
    "organoResolvio": "PLENO",
    "huellaDigital": "6df7c46af3b3767505706d74df2b65f27e5316ef7edaaaee660ccd4dc5c13535",
    "fechaResolucion": "13/11/2025"
}