{
    "expediente": "3854/2025",
    "pertenencia": "PLENO",
    "ministro": "YASMÍN ESQUIVEL MOSSA",
    "resolucion": "ÚNICO. se desechan los recursos de revisión principal y adhesivos.",
    "votacion": "POR UNANIMIDAD DE NUEVE VOTOS DE LOS SEÑORES MINISTROS Y PRESIDENTE HUGO AGUILAR ORTIZ, LENIA BATRES GUADARRAMA, YASMÍN ESQUIVEL MOSSA (PONENTE), LORETTA ORTIZ AHLF, MARÍA ESTELA RÍOS GONZÁLEZ, GIOVANNI AZAEL FIGUEROA MEJÍA, IRVING ESPINOSA BETANZO, ARÍSTIDES RODRIGO GUERRERO GARCÍA, SARA IRENE HERRERÍAS GUERRA.",
    "urlInternet": "https://www2.scjn.gob.mx/juridica/engroses/3/2025/10/2_351621_7427.docx",
    "tema": "JUICIO DE NULIDAD EN CONTRA DE LA NEGATIVA DE DEDUCCIONES DE GASTOS FINANCIEROS.\r\n\r\nPOSIBLE TEMA DE PROCEDENCIA: INCONSTITUCIONALIDAD DEL 32, FRACCIÓN VI, DE LA LEY DEL IMPUESTO SOBRE LA RENTA VIGENTE EN DOS MIL TRECE.\r\n\r\nARGUMENTA VIOLACIÓN A LOS DERECHOS HUMANOS CONTENIDOS EN LOS ARTÍCULOS 14, 16 Y 31, FRACCIÓN IV, DE LA CONSTITUCIÓN POLÍTICA DE LOS ESTADOS UNIDOS MEXICANOS. \r\n\r\nCDV*CRA\r\n\r\nINCONSTITUCIONALIDAD DEL ARTÍCULO 32, FRACCIÓN VI,  DE LA LEY DEL IMPUESTO SOBRE LA RENTA, VIGENTE EN DOS MIL TRECE.",
    "organoJurisdiccionalOrigen": "TRIBUNAL DE ORIGEN: VIGÉSIMO PRIMER TRIBUNAL COLEGIADO EN MATERIA ADMINISTRATIVA DEL PRIMER CIRCUITO ",
    "organoResolvio": "PLENO",
    "huellaDigital": "677e667d382bbf4c6de8859b6229891d9cde1f771eab2c7ec680d679ba44e5ba",
    "fechaResolucion": "19/11/2025"
}