{
    "expediente": "72/2025-CA",
    "pertenencia": "PLENO",
    "ministro": "LENIA BATRES GUADARRAMA",
    "resolucion": "ÚNICO. Se desecha el recurso de reclamación.",
    "votacion": "ASÍ, LO RESOLVIÓ EL PLENO DE LA SUPREMA CORTE DE JUSTICIA DE LA NACIÓN POR MAYORÍA DE OCHO VOTOS DE LAS PERSONAS MINISTRAS HERRERÍAS GUERRA, RÍOS GONZÁLEZ, ESQUIVEL MOSSA, BATRES GUADARRAMA, ORTIZ AHLF, FIGUEROA MEJÍA, GUERRERO GARCÍA Y PRESIDENTE AGUILAR ORTIZ. EL SEÑOR MINISTRO ESPINOSA BETANZO VOTÓ EN CONTRA Y ANUNCIÓ VOTO PARTICULAR. \r\nEL SEÑOR MINISTRO PRESIDENTE AGUILAR ORTIZ DECLARÓ QUE EL ASUNTO SE RESOLVIÓ EN LOS TÉRMINOS PROPUESTOS.",
    "urlInternet": "https://www2.scjn.gob.mx/juridica/engroses/3/2025/30/2_355449_7451.docx",
    "tema": "CDV // EAL",
    "organoJurisdiccionalOrigen": "TRIBUNAL DE ORIGEN: NO DEFINIDO ",
    "organoResolvio": "PLENO",
    "huellaDigital": "f710e9cf1127399e4cc647b44cc9bb6f6f76a399fe87385d4d4b5d6cba317f13",
    "fechaResolucion": "04/12/2025"
}