{
    "idTesis": 2031200,
    "rubro": "QUEJA ADHESIVA. LA OMISIÓN DE SU REGULACIÓN EN LA LEY DE AMPARO ES CONSTITUCIONAL.",
    "texto": "Hechos: En un juicio de amparo indirecto se dictó un auto mediante el cual se desechó la ampliación propuesta por la parte quejosa respecto del cuestionario de la prueba pericial en psicología ofrecida por el tercero interesado. La solicitante del amparo interpuso recurso de queja. El tercero interesado planteó recurso de queja adhesiva, en el que argumentó la inconstitucionalidad de la Ley de Amparo, ante la omisión de regular expresamente dicho medio de impugnación, y limitar el derecho a una tutela judicial efectiva, igualdad procesal y acceso a un recurso judicial efectivo, lo que a su consideración es contrario a los artículos 17 de la Constitución Política de los Estados Unidos Mexicanos, así como 8, numeral 1, y 25 de la Convención Americana sobre Derechos Humanos.\r\n\r\nCriterio jurídico: Este Tribunal Colegiado de Circuito determina que la omisión de regular el recurso de queja adhesiva en la Ley de Amparo es constitucional.\r\n\r\nJustificación: La citada omisión no limita el derecho fundamental de las personas de acceder a tribunales judiciales imparciales a plantear el ejercicio de un derecho legítimo o defenderse de una pretensión instaurada en su contra con el fin de que a través de un proceso en el que se respeten ciertas formalidades, se decida sobre la protección o no de su derecho ejercido o de la defensa que se hubiera planteado; sino sólo a acceder a un recurso dentro del procedimiento de amparo, lo cual es constitucionalmente válido, pues si bien es cierto, no pueden imponerse a los justiciables condiciones de trámite y de aspecto meramente formal que impliquen la denegación de este derecho a la tutela jurisdiccional; también lo es que, en el caso, los requisitos de procedencia de una acción o un recurso, no son en sí mismos violatorios del artículo 17 constitucional, siempre y cuando sean razonables, proporcionales y no discriminatorios; cuestión que correspondería al promovente demostrar, es decir, que la ausencia de reconocimiento de la procedencia del recurso de queja adhesivo en la Ley de Amparo, es irracional, desproporcional o discriminatoria. La omisión de incluir la adhesión al recurso de queja, permite resolver este último en un menor tiempo y no impide a la contraparte del recurrente presentar algún escrito que pueda oponerse a la pretensión contenida en ese medio de defensa o incluso a su procedencia; lo que lleva a concluir que dicho trato es razonable y objetivo.\r\n\r\nSEGUNDO TRIBUNAL COLEGIADO EN MATERIA CIVIL DEL TERCER CIRCUITO.",
    "precedentes": "Queja 336/2023. 8 de diciembre de 2023. Unanimidad de votos. Ponente: Alberto Miguel Ruiz Matías. Secretario: Manuel Ayala Reyes.",
    "epoca": "Undécima Época",
    "instancia": "Tribunales Colegiados de Circuito",
    "organoJuris": "SEGUNDO TRIBUNAL COLEGIADO EN MATERIA CIVIL DEL TERCER CIRCUITO.",
    "fuente": "Gaceta del Semanario Judicial de la Federación",
    "tesis": "III.2o.C.23 K (11a.)",
    "tipoTesis": "Aislada",
    "localizacion": " [TA]; 11a. Época; T.C.C.; Gaceta S.J.F.; Libro 53, Septiembre de 2025; Tomo I, Volumen 1; Pág. 1027",
    "anio": 2025,
    "mes": "Septiembre",
    "notaPublica": "Esta tesis se publicó el viernes 05 de septiembre de 2025 a las 10:14 horas en el Semanario Judicial de la Federación.",
    "anexos": "",
    "huellaDigital": "2d4310dcc2932079c321d13f9a915ad2847047c0be88151b457f647d1f1aa732",
    "materias": [
        "Común",
        "Constitucional"
    ]
}